{
  "witty_responses": {
    "tired": [
      "Thakeko? Mobile ko battery jastai low power mode ma! 🔋",
      "Tired vanna lai 'Thakaye' vannu paryo! Nepali ma sounds better! 😴",
      "Energy tira gayera aaija, thaki haleko jasto cha! ⚡",
      "Thaki halyo = social interaction mode OFF! 🔌",
      "Tired huncha ki Netflix binge watch ko side effect! 📺💤",
      "Energy drink vs Natural rest - quick fix vs proper solution! ⚡💊",
      "Thakeko bela sabai kura negative lagcha, perspective change! 👀",
      "Power nap vs Full sleep - time management skill test! 😴⏰",
      "Tired face = filter lagayeko jastai automatic sad expression! 😔📸",
      "Weekend rest vs Weekday tiredness - never balanced equation! ⚖️",
      "Mentally tired vs Physically tired - different category, same feeling! 🧠💪",
      "Tired bhayera productivity drop - scientific explanation exists! 📊⬇️",
      "Rest is not luxury, it's necessity - adult realization! 😌✨",
      "Thaki haleko bela decision making capacity zero huncha! 🤯",
      "Energy conservation mode activated - minimal effort maximum rest! 🐌"
    ],
    "traffic": [
      "Kathmandu ko traffic: meditation practice ho, patience sikauchha! 🚗🙏",
      "Ring road ma stuck - time travel experience, past ma janchha! ⏰",
      "Traffic jam ma book padhna milchha, skill development! 📚🚌",
      "Traffic light = suggestion system, actual compliance optional! 🚦🤷",
      "Rush hour = daily migration, predictable chaos scheduled! 🚗🏃‍♂️",
      "Traffic police = modern warrior, brave soul road managing! 👮‍♂️⚔️",
      "Honking = communication method, emotional expression through sound! 📯🗣️",
      "Traffic rule = theoretical concept, practical application variable! 📋❓",
      "Parking space = treasure hunt, luck-based finding system! 🅿️🗺️",
      "Traffic patience = character building, anger management course! 😤➡️😌",
      "Road rage = emotional fitness test, self-control measurement! 😡🏋️",
      "Traffic update = modern news necessity, route planning essential! 📱🗺️",
      "Public transport vs Private vehicle - environmental vs convenience choice! 🚌🚗",
      "Traffic accident = reality check, driving awareness reminder! 💥⚠️",
      "Traffic solution = engineering challenge, urban planning complexity! 🏗️🧠"
    ],
    "cringe": [
      "Bold words from someone whose personality came from a group chat.",
      "That's rich coming from someone who thinks WiFi password is personal information.",
      "Says the person who still uses 'XD' unironically in 2025.",
      "Interesting perspective from someone whose idea of culture is Netflix recommendations.",
      "That's cute, did you learn that from your motivational calendar?",
      "Speaking of cringe, remember when you thought 'YOLO' was profound?",
      "That's adorable, like a participation trophy for having opinions.",
      "Wow, such wisdom from someone who asks Google how to spell 'definitely'.",
      "That's precious coming from someone whose bio says 'living my best life'.",
      "Rich words from someone who thinks astrology is a personality trait.",
      "That's sweet, did your inspirational quotes app tell you that?",
      "Fascinating insight from someone who peaked in high school group projects.",
      "That's endearing, like watching someone discover the internet for the first time.",
      "Bold statement from someone whose greatest achievement is a viral TikTok comment.",
      "That's touching, really shows the depth of your Pinterest philosophy board."
    ],
    "lado": [
      "Bandar Ko Chaak",
      "Bhalu",
      "Chickde",
      "Chickne",
      "Dhoti",
      "Goo kha",
      "Gula chus randi",
      "Jantha",
      "Kangres",
      "Lado",
      "Lado chus",
      "Lado kha",
      "Lado ko tuppo",
      "Lang Lang",
      "Randi",
      "Machikni",
      "Machikne",
      "Gawar",
      "Muji",
      "Prachanda",
      "Tutturay",
      "Beshya",
      "Bhalu ko poi",
      "chaak ko pwal",
      "chahk ko dulka",
      "condo",
      "condo hannay",
      "fushi kha",
      "gand faatdim",
      "gula kha",
      "kukur chikni",
      "laando kha",
      "lado",
      "mandale",
      "maobadi",
      "mero fushi kha",
      "murda",
      "randi ko choro",
      "puti kha",
      "randiko choro",
      "sungghur",
      "turi tauke",
      "muji",
      "mujii",
      "mujee",
      "muj1",
      "machikne",
      "machikney",
      "machikneya",
      "lado",
      "lado kha",
      "ladokha",
      "randi",
      "raandi",
      "radi",
      "harami",
      "haraami",
      "haraam",
      "chor",
      "chorey",
      "kukur",
      "kukkur",
      "gadha",
      "gaddha",
      "bhains",
      "bhainsa",
      "suar",
      "suwar",
      "pakhe",
      "pakhey",
      "bhate",
      "bhatey",
      "khate",
      "khatey",
      "gwache",
      "gwachey",
      "gwar",
      "lato",
      "latto",
      "murkha",
      "murkhey",
      "boka",
      "bokaa",
      "jhuto",
      "jhutha",
      "jhutho",
      "jhagralu",
      "jhagda",
      "ghatiya",
      "ghatya",
      "bekar",
      "bekaar",
      "faltu",
      "phaaltu",
      "nikamma",
      "nikama",
      "nalayak",
      "nalayek",
      "dhokebaaz",
      "dhokebaj",
      "chirkut",
      "chirkutya",
      "lafanga",
      "lafange",
      "badmash",
      "badmaash",
      "badtameez",
      "badtamiz",
      "tharki",
      "tharkey",
      "besharam",
      "besharm",
      "hawasi",
      "hawas",
      "ullu",
      "ullu jasto",
      "gadha jasto",
      "kukur jasto",
      "bhains jasto",
      "suar jasto",
      "pakhe jasto",
      "bhate jasto",
      "khate jasto",
      "lato jasto",
      "murkha jasto",
      "boka jasto",
      "jhuto manche",
      "ghatiya manche",
      "bekar manche",
      "faltu manche",
      "nalayak manche",
      "nikamma manche",
      "dhokebaaz manche",
      "chirkut manche",
      "lafanga manche",
      "badmash manche",
      "tharki manche",
      "besharam manche",
      "hawasi manche",
      "topibaaz",
      "topi lagayo",
      "topi lagyo",
      "dimag chaina",
      "buddhi chaina",
      "dimag kharab",
      "dimag bigryo",
      "tauko kharab",
      "manche ho ki",
      "manche hoina",
      "esto manche",
      "kasto manche",
      "yo muji",
      "tyo muji",
      "ta muji",
      "yo gadha",
      "tyo gadha",
      "ta gadha",
      "yo kukur",
      "tyo kukur",
      "ta kukur",
      "yo bhains",
      "tyo bhains",
      "ta bhains",
      "yo suar",
      "tyo suar",
      "ta suar",
      "yo pakhe",
      "tyo pakhe",
      "ta pakhe",
      "yo bhate",
      "tyo bhate",
      "ta bhate",
      "yo khate",
      "tyo khate",
      "ta khate",
      "yo lato",
      "tyo lato",
      "ta lato",
      "yo murkha",
      "tyo murkha",
      "ta murkha",
      "yo boka",
      "tyo boka",
      "ta boka",
      "yo chor",
      "tyo chor",
      "ta chor",
      "yo harami",
      "tyo harami",
      "ta harami",
      "yo randi",
      "tyo randi",
      "ta randi",
      "chup muji",
      "chup gadha",
      "chup kukur",
      "chup bhains",
      "chup suar",
      "bolna na aaune",
      "bolna na janne",
      "kaam chaina",
      "kaam ko chainas",
      "kaam lagdaina",
      "kaam nalagne",
      "bekar ko",
      "faltu ko",
      "jhuto ko",
      "chor ko",
      "harami ko",
      "muji ko",
      "gadha ko",
      "kukur ko",
      "bhains ko",
      "suar ko",
      "tero tauko",
      "tero dimag",
      "tero buddhi",
      "ta kasto",
      "ta kasto manche",
      "esto k",
      "esto kina",
      "kina esto",
      "kasto ho",
      "k ho ta",
      "ho ki hoina",
      "manche ho ki",
      "hoina jasto",
      "na ramro",
      "dherai bolchas",
      "dherai bolne",
      "bolna na aaune",
      "bolna na janne",
      "chup lag",
      "chup bas",
      "chup ta",
      "chup muji",
      "chup pakhe",
      "chup bhate",
      "chup khate",
      "chup gadha",
      "chup kukur",
      "chup bhains",
      "chup suar",
      "chup murkha",
      "chup boka",
      "chup chor",
      "chup harami",
      "chup randi",
      "kam chaina",
      "kaam chaina",
      "kaam ko chainas",
      "kaam ko hoina",
      "kaam lagdaina",
      "kaam lagne hoina",
      "kaam nalagne",
      "kaam ko manche hoina",
      "bekar ko",
      "faltu ko",
      "jhuto ko",
      "chor ko",
      "harami ko",
      "muji ko",
      "gadha ko",
      "kukur ko",
      "bhains ko",
      "suar ko",
      "pakhe ko",
      "bhate ko",
      "khate ko",
      "lato ko",
      "murkha ko",
      "boka ko",
      "jhuto manche",
      "jhuto kura",
      "jhuto bolne",
      "jhuto bolchas",
      "jhuto bolyo",
      "jhuto bolira",
      "jhagda garne",
      "jhagda garne manche",
      "jhagda matra",
      "jhagralu manche",
      "jhagralu ta",
      "ghatiya kura",
      "ghatiya kaam",
      "ghatiya soch",
      "ghatiya dimag",
      "bekar kura",
      "bekar kaam",
      "faltu kura",
      "faltu kaam",
      "nikamma ta",
      "nikamma manche",
      "nalayak ta",
      "nalayak manche",
      "dhokebaaz ta",
      "dhokebaaz manche",
      "dhoka dine",
      "dhoka diyo",
      "dhoka dincha",
      "chirkut ta",
      "chirkut manche",
      "lafanga ta",
      "lafanga manche",
      "badmash ta",
      "badmash manche",
      "badtamiz ta",
      "badtamiz manche",
      "tharki ta",
      "tharki manche",
      "besharam ta",
      "besharam manche",
      "hawasi ta",
      "hawasi manche",
      "topibaaz ta",
      "topi lagayera",
      "topi lagayo",
      "topi lagyo",
      "dimag gayo",
      "dimag bigryo",
      "dimag chaina",
      "buddhi chaina",
      "buddhi gayo",
      "tauko bigryo",
      "tauko kharab",
      "soch chaina",
      "soch kharab",
      "soch nai chaina",
      "esto dimag",
      "kasto dimag",
      "yo k ho",
      "tyo k ho",
      "ta k ho",
      "k ho yo",
      "k ho tyo",
      "k ho ta",
      "esto gadha",
      "esto kukur",
      "esto bhains",
      "esto suar",
      "esto pakhe",
      "esto bhate",
      "esto khate",
      "esto lato",
      "esto murkha",
      "esto boka",
      "esto chor",
      "esto harami",
      "esto randi",
      "kasto gadha",
      "kasto kukur",
      "kasto bhains",
      "kasto suar",
      "kasto pakhe",
      "kasto bhate",
      "kasto khate",
      "kasto lato",
      "kasto murkha",
      "kasto boka",
      "kasto chor",
      "kasto harami",
      "kasto randi"
    ],
    "randi": [
      "Bandar Ko Chaak",
      "Bhalu",
      "Chickde",
      "Chickne",
      "Dhoti",
      "Goo kha",
      "Gula chus randi",
      "Jantha",
      "Kangres",
      "Lado",
      "Lado chus",
      "Lado kha",
      "Lado ko tuppo",
      "Lang Lang",
      "Randi",
      "Machikni",
      "Machikne",
      "Gawar",
      "Muji",
      "Prachanda",
      "Tutturay",
      "Beshya",
      "Bhalu ko poi",
      "chaak ko pwal",
      "chahk ko dulka",
      "condo",
      "condo hannay",
      "fushi kha",
      "gand faatdim",
      "gula kha",
      "kukur chikni",
      "laando kha",
      "lado",
      "mandale",
      "maobadi",
      "mero fushi kha",
      "murda",
      "randi ko choro",
      "puti kha",
      "randiko choro",
      "sungghur",
      "turi tauke",
      "muji",
      "mujii",
      "mujee",
      "muj1",
      "machikne",
      "machikney",
      "machikneya",
      "lado",
      "lado kha",
      "ladokha",
      "randi",
      "raandi",
      "radi",
      "harami",
      "haraami",
      "haraam",
      "chor",
      "chorey",
      "kukur",
      "kukkur",
      "gadha",
      "gaddha",
      "bhains",
      "bhainsa",
      "suar",
      "suwar",
      "pakhe",
      "pakhey",
      "bhate",
      "bhatey",
      "khate",
      "khatey",
      "gwache",
      "gwachey",
      "gwar",
      "lato",
      "latto",
      "murkha",
      "murkhey",
      "boka",
      "bokaa",
      "jhuto",
      "jhutha",
      "jhutho",
      "jhagralu",
      "jhagda",
      "ghatiya",
      "ghatya",
      "bekar",
      "bekaar",
      "faltu",
      "phaaltu",
      "nikamma",
      "nikama",
      "nalayak",
      "nalayek",
      "dhokebaaz",
      "dhokebaj",
      "chirkut",
      "chirkutya",
      "lafanga",
      "lafange",
      "badmash",
      "badmaash",
      "badtameez",
      "badtamiz",
      "tharki",
      "tharkey",
      "besharam",
      "besharm",
      "hawasi",
      "hawas",
      "ullu",
      "ullu jasto",
      "gadha jasto",
      "kukur jasto",
      "bhains jasto",
      "suar jasto",
      "pakhe jasto",
      "bhate jasto",
      "khate jasto",
      "lato jasto",
      "murkha jasto",
      "boka jasto",
      "jhuto manche",
      "ghatiya manche",
      "bekar manche",
      "faltu manche",
      "nalayak manche",
      "nikamma manche",
      "dhokebaaz manche",
      "chirkut manche",
      "lafanga manche",
      "badmash manche",
      "tharki manche",
      "besharam manche",
      "hawasi manche",
      "topibaaz",
      "topi lagayo",
      "topi lagyo",
      "dimag chaina",
      "buddhi chaina",
      "dimag kharab",
      "dimag bigryo",
      "tauko kharab",
      "manche ho ki",
      "manche hoina",
      "esto manche",
      "kasto manche",
      "yo muji",
      "tyo muji",
      "ta muji",
      "yo gadha",
      "tyo gadha",
      "ta gadha",
      "yo kukur",
      "tyo kukur",
      "ta kukur",
      "yo bhains",
      "tyo bhains",
      "ta bhains",
      "yo suar",
      "tyo suar",
      "ta suar",
      "yo pakhe",
      "tyo pakhe",
      "ta pakhe",
      "yo bhate",
      "tyo bhate",
      "ta bhate",
      "yo khate",
      "tyo khate",
      "ta khate",
      "yo lato",
      "tyo lato",
      "ta lato",
      "yo murkha",
      "tyo murkha",
      "ta murkha",
      "yo boka",
      "tyo boka",
      "ta boka",
      "yo chor",
      "tyo chor",
      "ta chor",
      "yo harami",
      "tyo harami",
      "ta harami",
      "yo randi",
      "tyo randi",
      "ta randi",
      "chup muji",
      "chup gadha",
      "chup kukur",
      "chup bhains",
      "chup suar",
      "bolna na aaune",
      "bolna na janne",
      "kaam chaina",
      "kaam ko chainas",
      "kaam lagdaina",
      "kaam nalagne",
      "bekar ko",
      "faltu ko",
      "jhuto ko",
      "chor ko",
      "harami ko",
      "muji ko",
      "gadha ko",
      "kukur ko",
      "bhains ko",
      "suar ko",
      "tero tauko",
      "tero dimag",
      "tero buddhi",
      "ta kasto",
      "ta kasto manche",
      "esto k",
      "esto kina",
      "kina esto",
      "kasto ho",
      "k ho ta",
      "ho ki hoina",
      "manche ho ki",
      "hoina jasto",
      "na ramro",
      "dherai bolchas",
      "dherai bolne",
      "bolna na aaune",
      "bolna na janne",
      "chup lag",
      "chup bas",
      "chup ta",
      "chup muji",
      "chup pakhe",
      "chup bhate",
      "chup khate",
      "chup gadha",
      "chup kukur",
      "chup bhains",
      "chup suar",
      "chup murkha",
      "chup boka",
      "chup chor",
      "chup harami",
      "chup randi",
      "kam chaina",
      "kaam chaina",
      "kaam ko chainas",
      "kaam ko hoina",
      "kaam lagdaina",
      "kaam lagne hoina",
      "kaam nalagne",
      "kaam ko manche hoina",
      "bekar ko",
      "faltu ko",
      "jhuto ko",
      "chor ko",
      "harami ko",
      "muji ko",
      "gadha ko",
      "kukur ko",
      "bhains ko",
      "suar ko",
      "pakhe ko",
      "bhate ko",
      "khate ko",
      "lato ko",
      "murkha ko",
      "boka ko",
      "jhuto manche",
      "jhuto kura",
      "jhuto bolne",
      "jhuto bolchas",
      "jhuto bolyo",
      "jhuto bolira",
      "jhagda garne",
      "jhagda garne manche",
      "jhagda matra",
      "jhagralu manche",
      "jhagralu ta",
      "ghatiya kura",
      "ghatiya kaam",
      "ghatiya soch",
      "ghatiya dimag",
      "bekar kura",
      "bekar kaam",
      "faltu kura",
      "faltu kaam",
      "nikamma ta",
      "nikamma manche",
      "nalayak ta",
      "nalayak manche",
      "dhokebaaz ta",
      "dhokebaaz manche",
      "dhoka dine",
      "dhoka diyo",
      "dhoka dincha",
      "chirkut ta",
      "chirkut manche",
      "lafanga ta",
      "lafanga manche",
      "badmash ta",
      "badmash manche",
      "badtamiz ta",
      "badtamiz manche",
      "tharki ta",
      "tharki manche",
      "besharam ta",
      "besharam manche",
      "hawasi ta",
      "hawasi manche",
      "topibaaz ta",
      "topi lagayera",
      "topi lagayo",
      "topi lagyo",
      "dimag gayo",
      "dimag bigryo",
      "dimag chaina",
      "buddhi chaina",
      "buddhi gayo",
      "tauko bigryo",
      "tauko kharab",
      "soch chaina",
      "soch kharab",
      "soch nai chaina",
      "esto dimag",
      "kasto dimag",
      "yo k ho",
      "tyo k ho",
      "ta k ho",
      "k ho yo",
      "k ho tyo",
      "k ho ta",
      "esto gadha",
      "esto kukur",
      "esto bhains",
      "esto suar",
      "esto pakhe",
      "esto bhate",
      "esto khate",
      "esto lato",
      "esto murkha",
      "esto boka",
      "esto chor",
      "esto harami",
      "esto randi",
      "kasto gadha",
      "kasto kukur",
      "kasto bhains",
      "kasto suar",
      "kasto pakhe",
      "kasto bhate",
      "kasto khate",
      "kasto lato",
      "kasto murkha",
      "kasto boka",
      "kasto chor",
      "kasto harami",
      "kasto randi"
    ]
  },
  "welcome_messages": [
    "Welcome to Oli Bois {user}! — no rules, just vibes.",
    "You've officially entered the boi-zone {user}!",
    "This server is powered by beer, smokes, and chaos {user}!",
    "Welcome to the Oli Bois madhouse {user}! — leave your logic outside.",
    "Smoking? Drinking? Gaming? Perfect {user}! You belong here.",
    "Congratulations {user}!, you're now one of the degens.",
    "Oli Bois ain't a server, it's a whole damn vibe {user}!",
    "Grab a chair, light a cig, game on — welcome {user}!",
    "Welcome to the chill zone with zero chill {user}!",
    "We don't do normal here {user}! — welcome to the jungle.",
    "One of us, one of us — welcome, legend {user}!",
    "If you're reading this {user}!, you're already too deep.",
    "Oli Bois — where the pixels are lit and so are we {user}!",
    "Welcome to Oli Bois {user}!: the land of late nights and worse decisions.",
    "No entry fee, just pure madness {user}!",
    "This is your last stop before normalcy disappears {user}!",
    "Gaming, gossip, ganja — you're home now {user}!",
    "Say goodbye to productivity {user}! — Oli Bois just claimed you.",
    "This is where the chaos feels cozy {user}!",
    "Your sanity ends here — welcome {user}!",
    "Oli Bois: Not responsible for any hangovers {user}!",
    "Welcome, stranger {user}!. Take a shot, sit back.",
    "Make memes, not sense — that's how we do it {user}!",
    "10% game, 90% stupidity — 100% fun {user}!",
    "From Nepal to nowhere — Oli Bois rise {user}!",
    "Keep your volume low, the chaos is loud {user}!",
    "Welcome {user}! — hope your therapist is on speed dial.",
    "Log in, light up, level up {user}!",
    "One server to rule them all — and roast them all {user}!",
    "Welcome to Oli Bois {user}! — where the party never loads properly.",
    "Warning: This server contains high doses of dumb {user}!",
    "Leave your seriousness at the door {user}!",
    "Entry granted {user}!. IQ dropped instantly.",
    "Oli Bois — like your group chat, but unfiltered {user}!",
    "Welcome to where plans die and memes thrive {user}!",
    "Beer in one hand, controller in the other {user}!",
    "This isn't Discord, this is dis-chaos {user}!",
    "Come for the games, stay for the bullshit {user}!",
    "You have entered a no-sleep zone {user}!",
    "All-night chaos? Just another Tuesday here {user}!",
    "Welcome to the unholy combo of fun and regret {user}!",
    "Oli Bois — putting the 'lit' in 'legitimately insane' {user}!",
    "One server. Infinite vibes {user}!",
    "Welcome to where energy drinks cry for mercy {user}!",
    "Friends don't let friends stay sober on voice chat {user}!",
    "You thought you were normal? Cute {user}!",
    "Come as you are — leave as an Oli Boi {user}!",
    "Bro, you in? You in {user}!",
    "Where every 'yo' leads to a 5-hour call {user}!",
    "Welcome {user}! — now get weird with us.",
    "We're not toxic, we're spicy {user}!",
    "Welcome to the server that your mom warned you about {user}!",
    "Oli Bois: Because adulting is overrated {user}!",
    "We game hard, laugh harder {user}!",
    "Keep calm and spam emojis {user}!",
    "Come for the memes, stay for the late-night philosophy {user}!",
    "Oli Bois — breaking TOS since forever {user}!",
    "Enter the server, lose the plot {user}!",
    "We put the 'cha' in 'chat' {user}!",
    "Welcome to where drama is content {user}!",
    "Oli Bois: The only place lag is a lifestyle {user}!",
    "We don't crash games, we crash each other {user}!",
    "One chat, too many egos {user}!",
    "No cap, this server is cracked {user}!",
    "Welcome {user}! — we've been expecting your nonsense.",
    "Respect is earned. But here? Just be funny {user}!",
    "Sleep? We left that at the gate {user}!",
    "Welcome to the server that runs on caffeine and trauma {user}!",
    "Oli Bois: where plans get made and forgotten {user}!",
    "Enter loud, leave louder {user}!",
    "Let the games begin (and the braincells die) {user}!",
    "If stupidity was a server, it'd be this {user}!",
    "Welcome, soldier of chaos {user}!",
    "This ain't a phase, it's a lifestyle {user}!",
    "From lol to lmao — welcome aboard {user}!",
    "Welcome to where weekdays feel like weekends {user}!",
    "Oli Bois — we peak at 3 a.m. {user}!",
    "Welcome to where 'yo' means 20 things {user}!",
    "You just joined the most elite squad of nobodies {user}!",
    "Congrats {user}!! You made it to the bad decision zone.",
    "Don't ask for rules. There aren't any {user}!",
    "If you're here, you're already doomed (in the best way) {user}!",
    "Oli Bois is 90% noise and 10% more noise {user}!",
    "This server is sponsored by vibes and vapes {user}!",
    "Welcome to where everyone's mic is always cursed {user}!",
    "Game night? More like roast night {user}!",
    "Enter a chat, leave with trauma {user}!",
    "We put the 'bro' in broken sleep schedules {user}!",
    "It's not a cult. Yet {user}!",
    "Server motto: vibe hard, crash harder {user}!",
    "Welcome to the Nepali Avengers of Discord {user}!",
    "Your life just got significantly more unhinged {user}!",
    "Bring your problems — we'll roast them {user}!",
    "Welcome {user}! — now earn your nickname.",
    "Oli Bois — because therapy is expensive {user}!",
    "This is not a drill. This is real, chaotic energy {user}!",
    "In this server, everyone's a main character {user}!",
    "The lights are neon, the vibes are feral {user}!",
    "Type faster — the madness awaits {user}!",
    "Welcome, legend {user}!! You just joined the most gloriously useless server ever."
  ],
  "bot_config": {
    "samu_user_id": 783619741289414676,
    "welcome_channel_id": 762775973816696863,
    "samu_tag_reactions": ["🙈", "<:aww:786672671928614933>", "<a:flyingkisses:798813605033672714>"],
    "general_reactions": ["😂", "👍", "🤔", "😎", "🔥", "✨"],
    "write_command_user_id": 235006682583793664,
    "write_command_channel_id": 762775973816696863,
    "general_channel_id": 1496766118088671283,
    "confession_channel_id": 782141021211328522
  }
}